tplink/__init__.py
tplink/cli.py
tplink/tplink.py
tplink-0.2.3.dist-info/AUTHORS.rst
tplink-0.2.3.dist-info/LICENSE
tplink-0.2.3.dist-info/METADATA
tplink-0.2.3.dist-info/WHEEL
tplink-0.2.3.dist-info/entry_points.txt
tplink-0.2.3.dist-info/top_level.txt
tplink-0.2.3.dist-info/RECORD
