Metadata-Version: 2.1
Name: tplink
Version: 0.2.3
Summary: Get the list of hosts connected to the router
Home-page: https://github.com/JackNova/tplink
Author: Dario Iacampo
Author-email: dario@jntstudio.net
License: MIT license
Keywords: tplink
Platform: UNKNOWN
Classifier: Development Status :: 2 - Pre-Alpha
Classifier: Intended Audience :: Developers
Classifier: License :: OSI Approved :: MIT License
Classifier: Natural Language :: English
Classifier: Programming Language :: Python :: 3.5
Classifier: Programming Language :: Python :: 3.6
Requires-Dist: Click (>=6.0)
